web_and_file_utils/__init__.py
web_and_file_utils/filepack.py
web_and_file_utils/getdictstat.py
web_and_file_utils/getstat.py
web_and_file_utils/mailstat.py
web_and_file_utils-0.1.3.dist-info/LICENSE.txt
web_and_file_utils-0.1.3.dist-info/METADATA
web_and_file_utils-0.1.3.dist-info/WHEEL
web_and_file_utils-0.1.3.dist-info/top_level.txt
web_and_file_utils-0.1.3.dist-info/RECORD
