Metadata-Version: 2.1
Name: web-and-file-utils
Version: 0.1.3
Summary: Useful web and file utilities in Python
Home-page: https://github.com/Shriya99/web_and_file_utils
Author: Shriya Das
Author-email: shriya2017das@gmail.com
License: MIT
Keywords: Web Utilities,File Utilities,URL Status Checker,File Fetching
Platform: UNKNOWN
Classifier: Programming Language :: Python :: 3
Classifier: License :: OSI Approved :: MIT License
Classifier: Operating System :: OS Independent
